SQLBinance/__init__.py
SQLBinance/classData/_SQLBinance.py
SQLBinance/classData/comprobante_data.py
SQLBinance/classData/conexion.py
SQLBinance/classData/consulta.sql
SQLBinance/classData/informe_data.py
SQLBinance/classData/transaccion_data.py
SQLBinance/entidades/Comprobante.py
SQLBinance/entidades/Informe.py
SQLBinance/entidades/Transaccion.py
sqlbinance-0.0.4.dist-info/METADATA
sqlbinance-0.0.4.dist-info/WHEEL
sqlbinance-0.0.4.dist-info/licenses/LICENCE
sqlbinance-0.0.4.dist-info/RECORD
