Metadata-Version: 2.1
Name: SQLBinance
Version: 0.0.4
Summary: Librería para tomar las órdenes del comercio P2P De binance. Utiliza una base de datos SQLite, Manteniendo integridad y rapidez a la hora de tratar los datos
Project-URL: Homepage, https://github.com/FranDorrego/SQLbinance
Project-URL: Bug Tracker, https://github.com/pypa/sampleproject/issues
Author-email: Franco Dorrego <francodorrego@gmail.com>
License-File: LICENCE
Classifier: License :: OSI Approved :: MIT License
Classifier: Operating System :: OS Independent
Classifier: Programming Language :: Python :: 3
Requires-Python: >=3.7
